sbmf-0.0.14.dist-info/METADATA
sbmf-0.0.14.dist-info/WHEEL
sbmf-0.0.14.dist-info/licenses/LICENCE.txt
sbmf/sparse.cp311-win_amd64.pyd
sbmf/sparse.cp311-win_amd64.lib
sbmf-0.0.14.dist-info/RECORD
