Metadata-Version: 2.4
Name: sbmf
Version: 0.0.14
Summary: Utilities for sparse and semi-binary matrix factorization
Author-Email: Matteo Alleman <mmallemmann@gmail.com>
License-Expression: MIT
License-File: LICENCE.txt
Classifier: Programming Language :: Python :: 3
Classifier: Operating System :: OS Independent
Requires-Python: >=3.8
Requires-Dist: numpy
